{
    "libjulius-dev": {},
    "libomniorb4-dev": {},
    "libopkele-dev": {},
    "proftpd-dev": {},
    "guile-2.2-dev": {},
    "guile-3.0-dev": {},
    "mingw-w64-i686-dev": {},
    "libstdc++-10-dev": {},
    "libstdc++-11-dev": {},
    "libstdc++-12-dev": {},
    "libstdc++-9-dev": {},
    "libc6-dev": {},
    "nvidia-cuda-dev": {},
    "dietlibc-dev": {},
    "libnbcompat-dev": {},
    "libstdc++-arm-none-eabi-dev": {},
    "libnewlib-dev": {},
    "ruby3.0-dev": {},
    "libtbox-dev": {},
    "libwine-development-dev": {},
    "libwine-dev": {},
    "musl-dev": {},
    "iraf-dev": {},
    "libklibc-dev": {},
    "libc++-11-dev": {},
    "libc++-12-dev": {},
    "libc++-13-dev": {},
    "libc++-14-dev": {},
    "mingw-w64-x86-64-dev": {},
    "libfltk1.1-dev": {},
    "libfltk1.3-dev": {},
    "libfixposix-dev": {},
    "tcl8.6-dev": {},
    "libyaz-dev": {},
    "linux-libc-dev": {},
    "libexplain-dev": {},
    "libapriltag-dev": {},
    "libbsd-dev": {},
    "coop-computing-tools-dev": {},
    "libkpathsea-dev": {},
    "libmgba-dev": {},
    "libmupdf-dev": {},
    "libsnmp-dev": {},
    "libp4est-dev": {},
    "librust-capstone-sys-dev": {},
    "connman-dev": {},
    "libnl-3-dev": {},
    "liblwip-dev": {},
    "libbtrfs-dev": {},
    "libdrm-dev": {},
    "ntfs-3g-dev": {},
    "libfuse3-dev": {},
    "libnacore-dev": {},
    "libfmt-dev": {},
    "freerdp2-dev": {},
    "libzfslinux-dev": {},
    "liblog4cxx-dev": {},
    "notion-dev": {},
    "libopenbabel-dev": {},
    "paraview-dev": {},
    "libvtk9-dev": {},
    "libwinpr2-dev": {},
    "libcgal-dev": {},
    "libfcitx5utils-dev": {},
    "libisospec++-dev": {},
    "android-libandroidfw-dev": {},
    "android-libcutils-dev": {},
    "android-libutils-dev": {},
    "libbart-dev": {},
    "libbg-dev": {},
    "bitlbee-dev": {},
    "libc-client2007e-dev": {},
    "libcommoncpp2-dev": {},
    "libcctbx-dev": {},
    "libcliquer-dev": {},
    "libucommon-dev": {},
    "libcreaterepo-c-dev": {},
    "crtmpserver-dev": {},
    "libcrypto++-dev": {},
    "libwolfssl-dev": {},
    "libdart-external-odelcpsolver-dev": {},
    "cyclonedds-dev": {},
    "libdmraid-dev": {},
    "libdune-uggrid-dev": {},
    "libelk0-dev": {},
    "evolution-dev": {},
    "libfizmo-dev": {},
    "libfluidsynth-dev": {},
    "libgap-dev": {},
    "libgazebo-dev": {},
    "libgiac-dev": {},
    "libglyr-dev": {},
    "gmpc-dev": {},
    "libgtkmm-2.4-dev": {},
    "libgtkmm-3.0-dev": {},
    "libgwenhywfar-core-dev": {},
    "libstaden-read-dev": {},
    "hybrid-dev": {},
    "irssi-dev": {},
    "libitpp-dev": {},
    "liblastfm5-dev": {},
    "libhx-dev": {},
    "libchipcard-dev": {},
    "libdockapp-dev": {},
    "libinstpatch-dev": {},
    "libnitrokey-dev": {},
    "libnoise-dev": {},
    "liblinphone-dev": {},
    "lxpanel-dev": {},
    "libm4ri-dev": {},
    "libmadness-dev": {},
    "libmartchus-c++utilities-dev": {},
    "libncbi-vdb-dev": {},
    "libode-dev": {},
    "libopenwsman-dev": {},
    "libosmocore-dev": {},
    "libphat-dev": {},
    "prayer-templates-dev": {},
    "libroar-dev": {},
    "samba-dev": {},
    "libspooles-dev": {},
    "syslog-ng-dev": {},
    "libvalapanel-dev": {},
    "libnx-x11-dev": {},
    "libsimgrid-dev": {},
    "xserver-xorg-dev": {},
    "libbind-export-dev": {},
    "libkrb5-dev": {},
    "libbind-dev": {},
    "bind9-dev": {},
    "libcds-dev": {},
    "relacy-dev": {},
    "gauche-dev": {},
    "libclanlib-dev": {},
    "libgraphicsmagick1-dev": {},
    "ivtools-dev": {},
    "libkf5wayland-dev": {},
    "libkf5syndication-dev": {},
    "libcal3d12-dev": {},
    "libcoap2-dev": {},
    "libcoap3-dev": {},
    "libcpprest-dev": {},
    "libglibmm-2.4-dev": {},
    "libgloox-dev": {},
    "libapogee-dev": {},
    "libpipewire-0.3-dev": {},
    "librime-dev": {},
    "libsynfig-dev": {},
    "libtgowt-dev": {},
    "gcc-10-plugin-dev": {},
    "gcc-11-plugin-dev": {},
    "gcc-12-plugin-dev": {},
    "gcc-9-plugin-dev": {},
    "libarrayfire-dev": {},
    "libprocess-cpp-dev": {},
    "libproperties-cpp-dev": {},
    "libcxxtools-dev": {},
    "libell-dev": {},
    "libcamera-dev": {},
    "libgearman-dev": {},
    "libgtop2-dev": {},
    "mirtest-dev": {},
    "libnih-dev": {},
    "libobs-dev": {},
    "openbox-dev": {},
    "libsigc++-2.0-dev": {},
    "libwibble-dev": {},
    "libxmmsclient++-dev": {},
    "libktorrent-dev": {},
    "libclaws-mail-dev": {},
    "libclsync-dev": {},
    "libdcmtk-dev": {},
    "libowfat-dietlibc-dev": {},
    "foxeye-dev": {},
    "libgisi-dev": {},
    "libgnutls28-dev": {},
    "libguac-dev": {},
    "inspircd-dev": {},
    "kannel-dev": {},
    "libafterimage-dev": {},
    "libast2-dev": {},
    "liblog4cplus-dev": {},
    "liblscp-dev": {},
    "moarvm-dev": {},
    "libmpdclient-dev": {},
    "libns3-dev": {},
    "libntirpc-dev": {},
    "libp8-platform-dev": {},
    "libpcap0.8-dev": {},
    "libpgm-dev": {},
    "libowfat-dev": {},
    "libsylph-dev": {},
    "libtensorpipe-dev": {},
    "libwsutil-dev": {},
    "skalibs-dev": {},
    "libcolpack-dev": {},
    "libarpack2-dev": {},
    "libmemcached-dev": {},
    "libqhull-dev": {},
    "libscythestat-dev": {},
    "libycadgraywolf-dev": {},
    "golang-github-snapcore-snapd-dev": {},
    "casacore-dev": {},
    "libmarisa-dev": {},
    "libtagcoll2-dev": {},
    "libdfp-dev": {},
    "tk8.6-dev": {},
    "libball1.5-dev": {},
    "libcoin-dev": {},
    "libaal-dev": {},
    "libasmjit-dev": {},
    "libcln-dev": {},
    "compiz-dev": {},
    "libcvc4-dev": {},
    "libdebian-installer4-dev": {},
    "libdlib-dev": {},
    "libdpkg-dev": {},
    "libdx4-dev": {},
    "libept-dev": {},
    "libfst-dev": {},
    "libgloo-dev": {},
    "libgroonga-dev": {},
    "libcapnp-dev": {},
    "libhashkit-dev": {},
    "libmruby-dev": {},
    "libnop-dev": {},
    "libsc-dev": {},
    "libspa-0.2-dev": {},
    "libsrecord-dev": {},
    "libucx-dev": {},
    "libwreport-dev": {},
    "libatlas-ecmwf-dev": {},
    "libyaramod-dev": {},
    "libglusterfs-dev": {},
    "asterisk-dev": {},
    "libmailutils-dev": {},
    "libkf5akonadisearch-dev": {},
    "libncurses-dev": {},
    "libinsighttoolkit4-dev": {},
    "libinsighttoolkit5-dev": {},
    "libabsl-dev": {},
    "libdispatch-dev": {},
    "libenet-dev": {},
    "libfcl-dev": {},
    "libgrpc++-dev": {},
    "libgrpc-dev": {},
    "libmrpt-ros1bridge-dev": {},
    "libmyth-dev": {},
    "libpcl-dev": {},
    "libroscpp-core-dev": {},
    "libtntdb-dev": {},
    "libavutil-dev": {},
    "lv2-dev": {},
    "libdatrie-dev": {},
    "libeiskaltdcpp-dev": {},
    "gthumb-dev": {},
    "libwebrtc-audio-processing-dev": {},
    "libxtensor-blas-dev": {},
    "libgwyddion20-dev": {},
    "libkf5contacts-dev": {},
    "libmetview-dev": {},
    "libfcitx5core-dev": {},
    "libkf5purpose-dev": {},
    "libcdk5-dev": {},
    "libcwidget-dev": {},
    "audacious-dev": {},
    "libdbusmenu-gtk-dev": {},
    "libdbusmenu-gtk3-dev": {},
    "libt3widget-dev": {},
    "libvdk2-dev": {},
    "vdr-dev": {},
    "libgcc-10-dev": {},
    "libgcc-11-dev": {},
    "libgcc-12-dev": {},
    "libgcc-9-dev": {},
    "libclang-common-11-dev": {},
    "libclang-common-12-dev": {},
    "libclang-common-13-dev": {},
    "libclang-common-14-dev": {},
    "libpcc-dev": {},
    "libsocket++-dev": {},
    "libthrust-dev": {},
    "libuv1-dev": {},
    "libxen-dev": {},
    "libadolc-dev": {},
    "libopenafs-dev": {},
    "libfido2-dev": {},
    "libhud-client2-dev": {},
    "liblorene-dev": {},
    "libpolylib64-dev": {},
    "libroscpp-dev": {},
    "libtorrent-dev": {},
    "libclips-dev": {},
    "libgpac-dev": {},
    "libnblib-dev": {},
    "libwxbase3.0-dev": {},
    "libwxgtk3.0-gtk3-dev": {},
    "libhfsp-dev": {},
    "libkf5bluezqt-dev": {},
    "libkf5filemetadata-dev": {},
    "libkf5screen-dev": {},
    "libkf5kjs-dev": {},
    "libkpimgapi-dev": {},
    "libktp-dev": {},
    "liblief-dev": {},
    "libosp-dev": {},
    "libstopt-dev": {},
    "libtelepathy-logger-qt-dev": {},
    "vc-dev": {},
    "libassimp-dev": {},
    "libaubio-dev": {},
    "libavogadro-dev": {},
    "libbabeltrace2-dev": {},
    "libbellesip-dev": {},
    "libbotan-2-dev": {},
    "libbrotli-dev": {},
    "libtorch-dev": {},
    "libcairomm-1.0-dev": {},
    "libcdio-dev": {},
    "libceres-dev": {},
    "libcglm-dev": {},
    "libcriterion-dev": {},
    "libdbus-c++-dev": {},
    "libdc1394-dev": {},
    "libdeal.ii-dev": {},
    "dico-dev": {},
    "libdirectfb-dev": {},
    "libdolfinx-dev": {},
    "libec-dev": {},
    "libg3d-dev": {},
    "libganv-dev": {},
    "libgetdata-dev": {},
    "libgirara-dev": {},
    "libgit2-dev": {},
    "libglbinding-dev": {},
    "gnuradio-dev": {},
    "libgoocanvasmm-2.0-dev": {},
    "libgpuarray-dev": {},
    "libgraphviz-dev": {},
    "libgutenprint-dev": {},
    "libiceoryx-binding-c-dev": {},
    "libigloo-dev": {},
    "libisal-dev": {},
    "libjack-jackd2-dev": {},
    "libjack-dev": {},
    "lib3ds-dev": {},
    "libmuscle-dev": {},
    "libbde-dev": {},
    "libbfio-dev": {},
    "libcmis-dev": {},
    "libcork-dev": {},
    "libcreg-dev": {},
    "libdbusmenu-glib-dev": {},
    "libesedb-dev": {},
    "libevt-dev": {},
    "libevtx-dev": {},
    "libewf-dev": {},
    "libfsapfs-dev": {},
    "libfsext-dev": {},
    "libfshfs-dev": {},
    "libfsntfs-dev": {},
    "libfsxfs-dev": {},
    "libfvde-dev": {},
    "libfwnt-dev": {},
    "libfwsi-dev": {},
    "libgltf-dev": {},
    "libipset-dev": {},
    "libisns-dev": {},
    "liblnk-dev": {},
    "libluksde-dev": {},
    "libmawk-dev": {},
    "libmsiecf-dev": {},
    "libntru-0.5-dev": {},
    "libolecf-dev": {},
    "libopenraw-dev": {},
    "libpff-dev": {},
    "libpmemobj-dev": {},
    "libportal-dev": {},
    "libqcow-dev": {},
    "libregf-dev": {},
    "librepo-dev": {},
    "libscca-dev": {},
    "libsigscan-dev": {},
    "libsmdev-dev": {},
    "libsmraw-dev": {},
    "libvcdinfo-dev": {},
    "libvhdi-dev": {},
    "libvmdk-dev": {},
    "libvshadow-dev": {},
    "libvslvm-dev": {},
    "libwfut-0.2-dev": {},
    "libwmf-dev": {},
    "liblitehtml-dev": {},
    "libmircommon-dev": {},
    "libmps-dev": {},
    "libmptcpd3-dev": {},
    "libpaho-mqttpp-dev": {},
    "libmrpt-graphslam-dev": {},
    "libmrpt-vision-dev": {},
    "libmuffin-dev": {},
    "libmutter-10-dev": {},
    "ofono-dev": {},
    "libssl-dev": {},
    "libosd-dev": {},
    "libpangomm-1.4-dev": {},
    "libpappsomspp-dev": {},
    "libqpid-proton11-dev": {},
    "qt5qevercloud-dev": {},
    "librdkit-dev": {},
    "libreiser4-dev": {},
    "remmina-dev": {},
    "librgxg-dev": {},
    "librocksdb-dev": {},
    "libsimde-dev": {},
    "libsmartcardpp-dev": {},
    "libsmbios-dev": {},
    "libsopt-dev": {},
    "libspfft-dev": {},
    "libspice-protocol-dev": {},
    "libstxxl-dev": {},
    "libtelepathy-qt5-dev": {},
    "libtext-engine-dev": {},
    "libtirpc-dev": {},
    "libukwm-1-dev": {},
    "liburdfdom-headers-dev": {},
    "libvmatch-dev": {},
    "libvotca-tools-dev": {},
    "libvtk7-dev": {},
    "libwebp-dev": {},
    "libeckit-dev": {},
    "libpci-dev": {},
    "libxapian-dev": {},
    "libxfdashboard-dev": {},
    "libyara-dev": {},
    "zathura-dev": {},
    "libzzip-dev": {},
    "libopenmpi-dev": {},
    "golang-github-bep-gowebp-dev": {},
    "libregfi-dev": {},
    "dovecot-dev": {},
    "ocfs2-tools-dev": {},
    "libsphinxbase-dev": {},
    "libflac-dev": {},
    "cyrus-dev": {},
    "libdynarmic-dev": {},
    "libigdgmm-dev": {},
    "liblemon-dev": {},
    "librosconsole-dev": {},
    "librust-jemalloc-sys-dev": {},
    "calc-dev": {},
    "android-libbase-dev": {},
    "libboost1.74-dev": {},
    "libdmlc-dev": {},
    "libfaifa-dev": {},
    "libknot-dev": {},
    "libmongoclient-dev": {},
    "libmsgpack-dev": {},
    "libodil-dev": {},
    "libsoundio-dev": {},
    "libghc-raaz-dev": {},
    "libleptonica-dev": {},
    "libplb-dev": {},
    "libtins-dev": {},
    "libudt-dev": {},
    "libclucene-dev": {},
    "libqt5gstreamer-dev": {},
    "libtiledarray-dev": {},
    "libaccounts-qt5-dev": {},
    "liballegro5-dev": {},
    "libasound2-dev": {},
    "libapt-pkg-dev": {},
    "libaqbanking-dev": {},
    "libatf-dev": {},
    "libavahi-common-dev": {},
    "libbabeltrace-dev": {},
    "libcjose-dev": {},
    "libnet-cpp-dev": {},
    "libdleyna-core-1.0-dev": {},
    "libeb16-dev": {},
    "gap-dev": {},
    "libgfarm-dev": {},
    "libgnokii-dev": {},
    "libgpgmepp-dev": {},
    "libgstreamermm-1.0-dev": {},
    "libigdfcl-dev": {},
    "libjreen-qt5-dev": {},
    "liborocos-kdl-dev": {},
    "liblammps-dev": {},
    "libldns-dev": {},
    "libcgroup-dev": {},
    "libinsane-dev": {},
    "librnd3-dev": {},
    "libtcod-dev": {},
    "libuser1-dev": {},
    "libliggghts-dev": {},
    "liblinbox-dev": {},
    "libmathic-dev": {},
    "libmbedtls-dev": {},
    "libmrmpi-dev": {},
    "octave-dev": {},
    "libolm-dev": {},
    "libpulse-dev": {},
    "qbs-dev": {},
    "rapidjson-dev": {},
    "libsensors-dev": {},
    "libsoci-dev": {},
    "libsquashfs-dev": {},
    "libtaningia-dev": {},
    "libtiledb-dev": {},
    "libuhd-dev": {},
    "libvips-dev": {},
    "libwfmath-1.0-dev": {},
    "libwireplumber-0.4-dev": {},
    "libzim-dev": {},
    "libyang2-dev": {},
    "libinotifytools0-dev": {},
    "libplumb2-dev": {},
    "fcitx-libs-dev": {},
    "libnanomsg-dev": {},
    "libnng-dev": {},
    "liboauth2-dev": {},
    "pacemaker-dev": {},
    "libkml-dev": {},
    "regina-normal-dev": {},
    "libsepol-dev": {},
    "libclc-13-dev": {},
    "libclc-dev": {},
    "libclc-12-dev": {},
    "libclc-14-dev": {},
    "x11proto-dev": {},
    "libxcb-shm0-dev": {},
    "libopendht-dev": {},
    "libpsocksxx-dev": {},
    "libace-dev": {},
    "libreoffice-dev": {},
    "lib32stdc++-10-dev": {},
    "libx32stdc++-10-dev": {},
    "lib32stdc++-11-dev": {},
    "libx32stdc++-11-dev": {},
    "lib32stdc++-12-dev": {},
    "libx32stdc++-12-dev": {},
    "lib32stdc++-9-dev": {},
    "libx32stdc++-9-dev": {},
    "libsfcutil0-dev": {},
    "zsh-dev": {},
    "libyadifa-dev": {},
    "libflann-dev": {},
    "libgemmlowp-dev": {},
    "libgudhi-dev": {},
    "libjsoncpp-dev": {},
    "libopencv-flann-dev": {},
    "libwlroots-dev": {},
    "libzlcore-dev": {},
    "libxmltooling-dev": {},
    "libbctoolbox-dev": {},
    "libetpan-dev": {},
    "lib2geom-dev": {},
    "libflightcrew-dev": {},
    "libkf5threadweaver-dev": {},
    "apertium-dev": {},
    "libmysqlcppconn-dev": {},
    "libforge-dev": {},
    "libflint-dev": {},
    "libgrantlee5-dev": {},
    "libimage-transport-dev": {},
    "libinjeqt-dev": {},
    "libjsonrpccpp-dev": {},
    "lam4-dev": {},
    "libxml++2.6-dev": {},
    "lttoolbox-dev": {},
    "libmono-2.0-dev": {},
    "libnodeletlib-dev": {},
    "libparted-dev": {},
    "libglib2.0-dev": {},
    "libi2util-dev": {},
    "libfaiss-dev": {},
    "libgretl1-dev": {},
    "libloki-dev": {},
    "libmrpt-random-dev": {},
    "libosl-dev": {},
    "libseqan2-dev": {},
    "libseriousproton-dev": {},
    "libvlfeat-dev": {},
    "libcleri-dev": {},
    "libfreeradius-dev": {},
    "libwaei-dev": {},
    "libmozjs-78-dev": {},
    "libnmz7-dev": {},
    "libncbi6-dev": {},
    "librcsb-core-wrapper0-dev": {},
    "libtre-dev": {},
    "libicu-dev": {},
    "libtut-dev": {},
    "libogre-next-dev": {},
    "libgeomview-dev": {},
    "pybind11-dev": {},
    "libspandsp-dev": {},
    "libc++abi-11-dev": {},
    "libc++abi-12-dev": {},
    "libc++abi-13-dev": {},
    "libc++abi-14-dev": {},
    "libcgreen1-dev": {},
    "libonnx-dev": {},
    "libcgal-qt5-dev": {},
    "libkf5libkleo-dev": {},
    "liballegro4-dev": {},
    "android-libsepol-dev": {},
    "libarpack++2-dev": {},
    "libicapapi-dev": {},
    "libcld2-dev": {},
    "libfilament-dev": {},
    "libgstreamer-plugins-base1.0-dev": {},
    "janus-dev": {},
    "libjson-c-dev": {},
    "liblasso3-dev": {},
    "libdap-dev": {},
    "libpurple-dev": {},
    "libsuma-dev": {},
    "libmission-control-plugins-dev": {},
    "libnice-dev": {},
    "libsemanage-dev": {},
    "libsiconos-numerics-dev": {},
    "signond-dev": {},
    "libspatialite-dev": {},
    "libtelepathy-glib-dev": {},
    "libunicap2-dev": {},
    "liburcu-dev": {},
    "libkf5tnef-dev": {},
    "libkf5sysguard-dev": {},
    "libspdlog-dev": {},
    "libsource-highlight-dev": {},
    "libgromacs-dev": {},
    "libxslt1-dev": {},
    "libsass-dev": {},
    "golang-github-bep-golibsass-dev": {},
    "golang-github-wellington-go-libsass-dev": {},
    "libcjs-dev": {},
    "libdraco-dev": {},
    "libdrumstick-dev": {},
    "libgjs-dev": {},
    "libprotobuf-dev": {},
    "inn2-dev": {},
    "kea-dev": {},
    "libgkarrays-dev": {},
    "libmessage-filters-dev": {},
    "nettle-dev": {},
    "rapmap-dev": {},
    "librosbag-storage-dev": {},
    "librospack-dev": {},
    "libtopic-tools-dev": {},
    "libtrilinos-pliris-dev": {},
    "libghc-sdl-mixer-dev": {},
    "golang-github-google-certificate-transparency-dev": {},
    "libblitz0-dev": {},
    "libgfs-dev": {},
    "libisl-dev": {},
    "libtiled-dev": {},
    "libvotca-csg-dev": {},
    "libgdamm5.0-dev": {},
    "libnftnl-dev": {},
    "liblrcalc-dev": {},
    "libre2-dev": {},
    "libmariadbd-dev": {},
    "libecpg-dev": {},
    "libgstreamer1.0-dev": {},
    "libplib-dev": {},
    "android-libboringssl-dev": {},
    "libmypaint-dev": {},
    "libnode-dev": {},
    "libkf5jsembed-dev": {},
    "libgnuastro-dev": {},
    "liblttng-ust-dev": {},
    "libclhep-dev": {},
    "libsparsehash-dev": {},
    "libint2-dev": {},
    "llvm-11-dev": {},
    "llvm-12-dev": {},
    "llvm-13-dev": {},
    "llvm-14-dev": {},
    "libmapnik-dev": {},
    "libapbs-dev": {},
    "libgeos++-dev": {},
    "libccrtp-dev": {},
    "libflatbuffers-dev": {},
    "libhwy-dev": {},
    "liblzma-dev": {},
    "libmgl-dev": {},
    "libminidjvu-dev": {},
    "libpappl-dev": {},
    "libsaml-dev": {},
    "libshibresolver-dev": {},
    "libshibsp-dev": {},
    "libxgboost-dev": {},
    "libxmlrpc-core-c3-dev": {},
    "librust-ring-dev": {},
    "librviz-dev": {},
    "libchibi-scheme-dev": {},
    "muroard-dev": {},
    "librbd-dev": {},
    "libfuntools-dev": {},
    "libleveldb-dev": {},
    "libyaml-cpp-dev": {},
    "libwiretap-dev": {},
    "libopenimageio-dev": {},
    "libkpmcore-dev": {},
    "libiberty-dev": {},
    "libomxil-bellagio-dev": {},
    "libgroove-dev": {},
    "libite-dev": {},
    "publib-dev": {},
    "libsolv-dev": {},
    "libxlsxwriter-dev": {},
    "libxmlrpc-epi-dev": {},
    "grass-dev": {},
    "libkf5networkmanagerqt-dev": {},
    "libkf5sonnet-dev": {},
    "codeblocks-dev": {},
    "libgvm-dev": {},
    "libquotient-dev": {},
    "plasma-workspace-dev": {},
    "libvotca-xtp-dev": {},
    "libcombblas-dev": {},
    "libcbor-dev": {},
    "libopentracing-dev": {},
    "libbrial-dev": {},
    "librust-tree-sitter-tags-dev": {},
    "libappstreamqt-dev": {},
    "libkf5identitymanagement-dev": {},
    "libkf5calendarsupport-dev": {},
    "libkproperty3-dev": {},
    "libkwaylandserver-dev": {},
    "libimecore-dev": {},
    "libafflib-dev": {},
    "libavifile-0.7-dev": {},
    "libayatana-common-dev": {},
    "libblockdev-utils-dev": {},
    "libbwa-dev": {},
    "libcppdb-dev": {},
    "libdiscover-dev": {},
    "libdouble-conversion-dev": {
        "utils.h": [],
        "bignum-dtoa.h": [],
        "bignum.h": [],
        "cached-powers.h": [],
        "diy-fp.h": [],
        "double-conversion.h": [],
        "double-to-string.h": [],
        "fast-dtoa.h": [],
        "fixed-dtoa.h": [],
        "ieee.h": [],
        "string-to-double.h": [],
        "strtod.h": []
    },
    "libatlas-cpp-0.6-dev": {},
    "libngs-sdk-dev": {},
    "libunistring-dev": {},
    "libcsmith-dev": {},
    "libanfo0-dev": {},
    "libquicktree-dev": {},
    "libsquizz-dev": {},
    "libfreefem++-dev": {},
    "ctn-dev": {},
    "libcvd-dev": {},
    "libnova-dev": {},
    "libmysql++-dev": {},
    "librttr-dev": {},
    "libgoogle-perftools-dev": {},
    "libhighwayhash-dev": {},
    "libd3dadapter9-mesa-dev": {},
    "libmeschach-dev": {},
    "libtgl-0.0.0.20160623-dev": {},
    "libyuma-dev": {},
    "win-iconv-mingw-w64-dev": {},
    "libiconv-hook-dev": {},
    "android-libadb-dev": {},
    "libatm1-dev": {},
    "libbpf-dev": {},
    "libsuitesparse-dev": {},
    "libblockdev-btrfs-dev": {},
    "golang-github-containerd-btrfs-dev": {},
    "lldpad-dev": {},
    "libadplug-dev": {},
    "libcap-dev": {},
    "libtesseract-dev": {},
    "libcompizconfig0-dev": {},
    "libcec-dev": {},
    "libcoda-dev": {},
    "libhwloc-dev": {},
    "libcxl-dev": {},
    "libndctl-dev": {},
    "libdnet-dev": {},
    "libaudio-dev": {},
    "libgmerlin-dev": {},
    "libpcaudio-dev": {},
    "libwpebackend-fdo-1.0-dev": {},
    "libcalcium-dev": {},
    "libeac-dev": {},
    "libdebconfclient0-dev": {},
    "libxine2-dev": {},
    "libkf5attica-dev": {},
    "libkf5activities-dev": {},
    "libkf5alarmcalendar-dev": {},
    "libkf5package-dev": {},
    "libkf5plasma-dev": {},
    "libntl-dev": {},
    "libobjcryst-dev": {},
    "libsfcgal-dev": {},
    "libaxtls-dev": {},
    "libbasix-dev": {},
    "libblimps3-dev": {},
    "libboinc-app-dev": {},
    "libcddb2-dev": {},
    "libchardet-dev": {},
    "libcharls-dev": {},
    "libclustalo-dev": {},
    "libcodec2-dev": {},
    "libcsound64-dev": {},
    "libdav1d-dev": {},
    "libdnswire-dev": {},
    "libdvdnav-dev": {},
    "libdvdread-dev": {},
    "libelf-dev": {},
    "facter-dev": {},
    "libfixbuf-dev": {},
    "libgav1-dev": {},
    "libgenht1-dev": {},
    "libginac-dev": {},
    "libgtkglextmm-x11-1.2-dev": {},
    "libcpp-hocon-dev": {},
    "libibtk-dev": {},
    "libidzebra-2.0-dev": {},
    "libismrmrd-dev": {},
    "libkiwix-dev": {},
    "libecap3-dev": {},
    "libjaylink-dev": {},
    "libotr5-dev": {},
    "libsigrok-dev": {},
    "libsigrokdecode-dev": {},
    "libstellarsolver-dev": {},
    "libweston-9-dev": {},
    "libwnck-3-dev": {},
    "libyuv-dev": {},
    "liblo10k1-dev": {},
    "liblog4c-dev": {},
    "liblxc-dev": {},
    "libmash-dev": {},
    "libmimetic-dev": {},
    "libmiral-dev": {},
    "libmirserver-dev": {},
    "libmovit-dev": {},
    "libmrpt-common-dev": {},
    "libnats-dev": {},
    "libnghttp3-dev": {},
    "libngtcp2-dev": {},
    "libnotcurses-core-dev": {},
    "okular-dev": {},
    "libomnievents-dev": {},
    "libtbb-dev": {},
    "libopenobex2-dev": {},
    "libopenvdb-dev": {},
    "libpano13-dev": {},
    "libprocps-dev": {},
    "libpskc-dev": {},
    "libpynac-dev": {},
    "libradcli-dev": {},
    "librxp-dev": {},
    "libsidplay1-dev": {},
    "libsimgear-dev": {},
    "libsodium-dev": {},
    "libsrt-gnutls-dev": {},
    "libsrt-openssl-dev": {},
    "libstlink-dev": {},
    "libswami-dev": {},
    "libsysrepo-dev": {},
    "libsysstat-qt5-0-dev": {},
    "libtinyframe-dev": {},
    "libui-gxmlcpp-dev": {},
    "libui-utilcpp-dev": {},
    "libuim-dev": {},
    "libcodcif-dev": {},
    "libwpe-1.0-dev": {},
    "libavcodec-dev": {},
    "libavdevice-dev": {},
    "libavfilter-dev": {},
    "libavformat-dev": {},
    "libpostproc-dev": {},
    "libswresample-dev": {},
    "libswscale-dev": {},
    "libqtav-dev": {},
    "libxmlsec1-dev": {},
    "znc-dev": {},
    "libgnat-util10-dev": {},
    "libgnatvsn9-dev": {},
    "golang-android-soong-dev": {},
    "gem-dev": {},
    "libmircore-dev": {},
    "clearsilver-dev": {},
    "liborocos-bfl-dev": {},
    "libodin-dev": {},
    "libpcl-ros-dev": {},
    "libblockdev-fs-dev": {},
    "libsquashfuse-dev": {},
    "libfuse-dev": {},
    "libgtp-dev": {},
    "euslisp-dev": {},
    "libdumbnet-dev": {},
    "libwvstreams-dev": {},
    "libevent-dev": {},
    "libgtksourceviewmm-3.0-dev": {},
    "libmems-dev": {},
    "libmirplatform-dev": {},
    "isc-dhcp-dev": {},
    "libradospp-dev": {},
    "libsoldout-dev": {},
    "libtf2-ros-dev": {},
    "libdvbpsi-dev": {},
    "liblirc-dev": {},
    "libanthyinput-dev": {},
    "libestools-dev": {},
    "libxgks-dev": {},
    "liburing-dev": {},
    "libbitstream-dev": {},
    "librtr-dev": {},
    "golang-github-jouyouyun-hardware-dev": {},
    "libwireshark-dev": {},
    "libcapi20-dev": {},
    "libblockdev-loop-dev": {},
    "libmagic-dev": {},
    "ppp-dev": {},
    "libsnapd-qt-dev": {},
    "libkf5pulseaudioqt-dev": {},
    "libcvm1-dev": {},
    "tarantool-dev": {},
    "libumlib-dev": {},
    "libxplc0.3.13-dev": {},
    "libopenipmi-dev": {},
    "libcwnn-dev": {},
    "libgavl-dev": {},
    "libkwnn-dev": {},
    "libsofia-sip-ua-dev": {},
    "libupb-dev": {},
    "libwnn-dev": {},
    "libwnn6-dev": {},
    "libnetconf2-dev": {},
    "libnfc-dev": {},
    "libflac++-dev": {},
    "libkubuntu-dev": {},
    "libcm256cc-dev": {},
    "libdsdcc-dev": {},
    "libgeos-dev": {},
    "libleatherman-dev": {},
    "libphonon4qt5experimental-dev": {},
    "golang-github-mdlayher-wifi-dev": {},
    "libpfm4-dev": {},
    "gpsim-dev": {},
    "libf2fs-dev": {},
    "libtorrent-rasterbar-dev": {},
    "libsctp-dev": {},
    "libseccomp-dev": {},
    "libcxx-serial-dev": {},
    "oss4-dev": {},
    "librust-sysinfo-dev": {},
    "libepc-dev": {},
    "libtls-dev": {},
    "libtty-dev": {},
    "libobexftp0-dev": {},
    "libossp-uuid-dev": {},
    "uuid-dev": {},
    "libiw-dev": {},
    "android-libext4-utils-dev": {},
    "libattr1-dev": {},
    "libarb-dev": {},
    "libdebug0-dev": {},
    "libmrpt-system-dev": {},
    "libsbml5-dev": {},
    "libvw-dev": {},
    "libgc-dev": {},
    "libnss3-dev": {},
    "gammaray-dev": {},
    "libtoontag-dev": {},
    "libvte-dev": {},
    "libibverbs-dev": {},
    "libdssialsacompat-dev": {},
    "libdvbv5-dev": {},
    "librpm-dev": {},
    "librust-clang-sys-dev": {},
    "doctest-dev": {},
    "librust-cexpr-dev": {},
    "libcups2-dev": {},
    "baloo-kf5-dev": {},
    "libkpimitinerary-dev": {},
    "libfstrm-dev": {},
    "libgoffice-0.10-dev": {},
    "php8.1-dev": {},
    "libblockdev-swap-dev": {},
    "liblightdm-gobject-1-dev": {},
    "libballview1.5-dev": {},
    "libxml2-dev": {},
    "libqpx-dev": {},
    "libmiroil-dev": {},
    "libccd-dev": {},
    "librheolef-dev": {},
    "libconsole-bridge-dev": {},
    "libqgis-dev": {},
    "libstarlink-pal-dev": {},
    "libpantomime-dev": {},
    "android-libfec-dev": {},
    "libavro-dev": {},
    "libjose-dev": {},
    "libparasail-dev": {},
    "libsvm-dev": {},
    "pktools-dev": {},
    "libpwiz-dev": {},
    "libatomic-ops-dev": {},
    "libcapstone-dev": {},
    "libgl-dev": {},
    "libgles-dev": {},
    "libogre-1.9-dev": {},
    "libepoxy-dev": {},
    "libogre-1.12-dev": {},
    "libgtkglext1-dev": {},
    "libocct-visualization-dev": {},
    "libglu1-mesa-dev": {},
    "libglx-dev": {},
    "libassuan-mingw-w64-dev": {},
    "libassuan-dev": {},
    "libemf-dev": {},
    "libaribb24-dev": {},
    "libcorkipset-dev": {},
    "libmetkit-dev": {},
    "libqd-dev": {},
    "libcfg-dev": {},
    "libkf5akonadi-dev": {},
    "libalsaplayer-dev": {},
    "libfpga-dev": {},
    "libcpl-dev": {},
    "directx-headers-dev": {},
    "libi2c-dev": {},
    "libplacebo-dev": {},
    "libastrometry-dev": {},
    "libmapcache1-dev": {},
    "libnih-dbus-dev": {},
    "libpog-dev": {},
    "libbibutils-dev": {},
    "libgcrypt-mingw-w64-dev": {},
    "libgcrypt20-dev": {},
    "libgpg-error-mingw-w64-dev": {},
    "libgpg-error-dev": {},
    "libjxr-dev": {},
    "libkf5kio-dev": {},
    "librtmp-dev": {},
    "libtntnet-dev": {},
    "kopano-dev": {},
    "libksba-mingw-w64-dev": {},
    "libksba-dev": {},
    "libytnef0-dev": {},
    "libesnacc-dev": {},
    "libsfst1-1.4-dev": {},
    "libmilter-dev": {},
    "trafficserver-dev": {},
    "libnpth-mingw-w64-dev": {},
    "libnpth0-dev": {},
    "libbrlapi-dev": {},
    "libgss-dev": {},
    "libgwengui-fox16-dev": {},
    "liboidc-agent-dev": {},
    "libopendbx1-dev": {},
    "libtranscript-dev": {},
    "libtree-sitter-dev": {},
    "librust-tree-sitter-dev": {},
    "libiodbc2-dev": {},
    "unixodbc-dev": {},
    "freetds-dev": {},
    "libbpp-raa-dev": {},
    "libbelr-dev": {},
    "libevhtp-dev": {},
    "libprotoc-dev": {},
    "libhtmlcxx-dev": {},
    "libee-dev": {},
    "liblognorm-dev": {},
    "libsurgescript-dev": {},
    "liburdf-parser-plugin-dev": {},
    "libbdd-dev": {},
    "libkf5su-dev": {},
    "open-vm-tools-dev": {},
    "libdbustest1-dev": {},
    "libkafs-client-dev": {},
    "libsdl-console-dev": {},
    "libecl-dev": {},
    "libfml-dev": {},
    "libkf5newstuff-dev": {},
    "libxext-dev": {},
    "nx-x11proto-xext-dev": {},
    "libtspi-dev": {},
    "libgxwmm-dev": {},
    "libusb-dev": {},
    "liblldb-11-dev": {},
    "liblldb-12-dev": {},
    "liblldb-13-dev": {},
    "liblldb-14-dev": {},
    "libpcsclite-dev": {},
    "libkf5cddb-dev": {},
    "libkf5xmlrpcclient-dev": {},
    "libavahi-client-dev": {},
    "libdynamic-reconfigure-config-init-mutex-dev": {},
    "liblxqt-globalkeys0-dev": {},
    "libmolequeue-dev": {},
    "libmpv-dev": {},
    "libriemann-client-dev": {},
    "libiso9660-dev": {},
    "libxcb-xinput-dev": {},
    "libz-mingw-w64-dev": {},
    "libpoco-dev": {},
    "zlib1g-dev": {},
    "libdewalls-dev": {},
    "libsx-dev": {},
    "libgutenprintui2-dev": {},
    "libsignal-protocol-c-dev": {},
    "libgnomecanvasmm-2.6-dev": {},
    "liblinear-dev": {},
    "libanalitza-dev": {},
    "libfasttext-dev": {},
    "libfplll-dev": {},
    "genius-dev": {},
    "libglm-dev": {},
    "libpsi3-dev": {},
    "libghc-vector-dev": {},
    "libghc-vector-algorithms-dev": {},
    "libgmsh-private-headers-dev": {},
    "libirrlicht-dev": {},
    "kdevelop-dev": {},
    "liblttng-ctl-dev": {},
    "libphonon4qt5-dev": {},
    "libdynamicedt3d-dev": {},
    "golang-github-ddevault-go-libvterm-dev": {},
    "libindi-dev": {},
    "libminc-dev": {},
    "libacexml-dev": {},
    "libmozjs-91-dev": {},
    "libclang-11-dev": {},
    "libclang-12-dev": {},
    "libclang-13-dev": {},
    "libmlir-13-dev": {},
    "libclang-14-dev": {},
    "libmlir-14-dev": {},
    "libantlr4-runtime-dev": {},
    "liblucene++-dev": {},
    "libstatgen-dev": {},
    "liblld-11-dev": {},
    "liblld-12-dev": {},
    "liblld-13-dev": {},
    "liblld-14-dev": {},
    "libfield3d-dev": {},
    "libgraphicsmagick++1-dev": {},
    "libzeroc-ice-dev": {},
    "libnux-4.0-dev": {},
    "libopenms-dev": {},
    "libcppunit-dev": {},
    "libfastcdr-dev": {},
    "libfastrtps-dev": {},
    "libfuzzylite-dev": {},
    "liblomiri-api-dev": {},
    "libompl-dev": {},
    "libwsman-clientpp-dev": {},
    "libsimbody-dev": {},
    "libsnapper-dev": {},
    "libthrift-dev": {},
    "libunity-api-dev": {},
    "librobottestingframework-dev": {},
    "libzypp-dev": {},
    "libzbar-dev": {},
    "libzdb-dev": {},
    "libpbbam-dev": {},
    "libfrog-dev": {},
    "libmedialibrary-dev": {},
    "libpbcopper-dev": {},
    "libpoppler-private-dev": {},
    "libquickfix-dev": {},
    "libann-dev": {},
    "libmadlib-dev": {},
    "libasl-dev": {},
    "libkf5imap-dev": {},
    "libacl1-dev": {},
    "vecgeom-dev": {},
    "android-libbacktrace-dev": {},
    "cauchy-dev": {},
    "libgeographic-dev": {},
    "libcsfml-dev": {},
    "libsoapysdr-dev": {},
    "libunittest++-dev": {},
    "libmygpo-qt-dev": {},
    "pinball-dev": {},
    "libcegui-mk2-dev": {},
    "libfdb5-dev": {},
    "libzthread-dev": {},
    "liboclgrind-dev": {},
    "libopenmm-dev": {},
    "libola-dev": {},
    "libopen3d-dev": {},
    "libbpp-core-dev": {},
    "libstk-dev": {},
    "nordugrid-arc-dev": {},
    "xaw3dg-dev": {},
    "libxaw3dxft8-dev": {},
    "xpaint-dev": {},
    "libmagics++-dev": {},
    "veccore-dev": {},
    "libtf-dev": {},
    "libtf2-dev": {},
    "libwaili-dev": {},
    "libchemps2-dev": {},
    "libeigen3-dev": {},
    "libzen-dev": {},
    "libzydis-dev": {},
    "juffed-dev": {},
    "liboctomap-dev": {},
    "libopenzwave1.6-dev": {},
    "libgdf-dev": {},
    "libhepmc3-dev": {},
    "libexadrums-dev": {},
    "libspatialindex-dev": {},
    "libticcutils-dev": {},
    "libdime-dev": {},
    "libplist++-dev": {},
    "libtulip-dev": {},
    "libxaw7-dev": {},
    "libmotif-dev": {},
    "libzycore-dev": {},
    "libmusicbrainz5-dev": {},
    "libcamitk-dev": {},
    "libsensor-msgs-dev": {},
    "libplanarity-dev": {},
    "liberis-1.3-dev": {},
    "libopenshot-dev": {},
    "libsimtkmolmodel-dev": {},
    "libodc-dev": {},
    "libarcus-dev": {},
    "libsavitar-dev": {},
    "libcephfs-dev": {},
    "libenki-dev": {},
    "glslang-dev": {},
    "libgraphite2-dev": {},
    "lzma-dev": {},
    "libblasr-dev": {},
    "libpbdata-dev": {},
    "libqpdf-dev": {},
    "libsdbus-c++-dev": {},
    "libtimbl-dev": {},
    "librapidcheck-dev": {},
    "libdlpack-dev": {},
    "libzxingcore-dev": {},
    "libunity-core-6.0-dev": {},
    "libadwaitaqt-dev": {},
    "libadwaita-1-dev": {},
    "libdiagnostic-aggregator-dev": {},
    "libclipper-dev": {},
    "qttools5-dev": {},
    "qt6-tools-dev": {},
    "libcantor-dev": {},
    "libdt-utils-dev": {},
    "gocr-dev": {},
    "libkaz-dev": {},
    "liberasurecode-dev": {},
    "libupnp-dev": {},
    "libworkflow-dev": {},
    "kross-dev": {},
    "libatkmm-1.6-dev": {},
    "libcitygml-dev": {},
    "libmrpt-nanogui-dev": {},
    "pypy3-dev": {},
    "libpython2.7-dev": {},
    "libpython3.10-dev": {},
    "pypy-dev": {},
    "libkf5unitconversion-dev": {
        "value.h": [],
        "converter.h": [],
        "unit.h": []
    },
    "libvarconf-dev": {},
    "libsidplay2-dev": {},
    "libkf5mediawiki-dev": {},
    "libcupsfilters-dev": {},
    "libiec16022-dev": {},
    "libvibrant6-dev": {},
    "libdislocker0-dev": {},
    "libsaga-dev": {},
    "libglobjects-dev": {},
    "libncarg-dev": {},
    "librlog-dev": {},
    "libtse3-dev": {},
    "libace-rmcast-dev": {},
    "libassa-3.5-5-dev": {},
    "libebml-dev": {},
    "libhepmc3-search-dev": {},
    "libsndobj-dev": {},
    "libqm-dsp-dev": {},
    "libqtermwidget5-0-dev": {},
    "libwxsvg-dev": {},
    "libdyssol-dev": {},
    "libkf5texteditor-dev": {},
    "libtango-dev": {},
    "libfishsound1-dev": {},
    "libexttextcat-dev": {},
    "libvolk2-dev": {},
    "libkf5people-dev": {},
    "libcbf-dev": {},
    "libsscm-dev": {},
    "libchewing3-dev": {},
    "libmatchbox-dev": {},
    "libfastjetplugins-dev": {},
    "libsiscone-dev": {},
    "libsiscone-spherical-dev": {},
    "libsnacc-dev": {},
    "libterralib-dev": {},
    "libzopfli-dev": {},
    "yorick-dev": {},
    "libgtkspellmm-3.0-dev": {},
    "libglademm-2.4-dev": {},
    "liboce-visualization-dev": {},
    "libocct-draw-dev": {},
    "libbenchmark-dev": {},
    "nx-x11proto-composite-dev": {},
    "libxcb-composite0-dev": {},
    "libkf5kdelibs4support-dev": {},
    "libqtav-private-dev": {},
    "libkf5solid-dev": {},
    "libimage-proc-dev": {},
    "libstereo-image-proc-dev": {},
    "libkf5calendarcore-dev": {},
    "libostyle-dev": {},
    "libifcplusplus-dev": {},
    "libcutl-dev": {},
    "enlightenment-dev": {},
    "exim4-dev": {},
    "libexiv2-dev": {},
    "libfastjet-dev": {},
    "libgclib-dev": {},
    "libgmt-dev": {},
    "libgvars3-dev": {},
    "libhmat-oss-dev": {},
    "libhmmer2-dev": {},
    "libhttrack-dev": {},
    "libinhomog-dev": {},
    "libjellyfish-2.0-dev": {},
    "liblfunction-dev": {},
    "libdmrconf-dev": {},
    "libdnf-dev": {},
    "libqtdbusmock1-dev": {},
    "libqtdbustest1-dev": {},
    "liblog4cpp5-dev": {},
    "liblog4shib-dev": {},
    "libnewmat10-dev": {},
    "libodb-boost-dev": {},
    "libodb-dev": {},
    "libodb-mysql-dev": {},
    "libodb-pgsql-dev": {},
    "libodb-qt-dev": {},
    "libodb-sqlite-dev": {},
    "libodsstream-dev": {},
    "libpcp3-dev": {},
    "libqapt-dev": {},
    "qcoro-qt5-dev": {},
    "qcoro-qt6-dev": {},
    "libripoff-dev": {},
    "libspatialaudio-dev": {},
    "libt3config-dev": {},
    "liblog4tango-dev": {},
    "libthrift-c-glib-dev": {},
    "libucpp-dev": {},
    "libexecline-dev": {},
    "pluginlib-dev": {},
    "libs6-dev": {},
    "libflorist2020-dev": {},
    "librust-lzma-sys-dev": {},
    "libsasl2-dev": {},
    "libtercpp-dev": {},
    "libopts25-dev": {},
    "neuron-dev": {},
    "libcurl4-gnutls-dev": {},
    "libcurl4-openssl-dev": {},
    "libcurl4-nss-dev": {},
    "libcneartree-dev": {},
    "osmo-libasn1c-dev": {},
    "libsdp-dev": {},
    "libhdf4-alt-dev": {},
    "libhdf4-dev": {},
    "libbondcpp-dev": {},
    "libgensio-dev": {},
    "libwnck-dev": {},
    "unagi-dev": {},
    "libdublintraceroute-dev": {},
    "libhat-trie-dev": {},
    "libcob4-dev": {},
    "libcob5-dev": {},
    "libprelude-dev": {},
    "libpst-dev": {},
    "libmarco-dev": {},
    "libmrpt-core-dev": {},
    "libopentracing-c-wrapper-dev": {},
    "libpackagekitqt5-dev": {},
    "libsunpinyin-dev": {},
    "libasynccore-dev": {},
    "librust-resvg-dev": {},
    "libzstd-dev": {},
    "golang-github-cilium-ebpf-dev": {},
    "libgfsgl-dev": {},
    "libfm-qt-dev": {},
    "libqaccessibilityclient-qt5-dev": {},
    "libalglib-dev": {},
    "libtriangle-dev": {},
    "libcpprspserver-dev": {},
    "libtbb2-dev": {},
    "libcppnumericalsolvers-dev": {},
    "libirstlm-dev": {},
    "libtclcl1-dev": {},
    "libmuparserx-dev": {},
    "libarmci-mpi-dev": {},
    "libobjc-10-dev": {},
    "libobjc-11-dev": {},
    "libobjc-12-dev": {},
    "libobjc-9-dev": {},
    "android-libselinux-dev": {},
    "libselinux1-dev": {},
    "libmorph-dev": {},
    "libmirrenderer-dev": {},
    "libkf5syntaxhighlighting-dev": {},
    "libblocksruntime-dev": {},
    "libbbhash-dev": {},
    "libgatbcore-dev": {},
    "liborthancframework-dev": {},
    "libopencv-apps-dev": {},
    "libpsurface-dev": {},
    "libmercator-0.3-dev": {},
    "libxbae-dev": {},
    "libqalculate-dev": {},
    "libccfits-dev": {},
    "libbpp-phyl-dev": {},
    "libdataquay-dev": {},
    "libbpp-popgen-dev": {},
    "libbpp-seq-dev": {},
    "libhfst-dev": {},
    "libfastahack-dev": {},
    "libxdmf-dev": {},
    "libcoverart-dev": {},
    "libkf5dav-dev": {},
    "libkf5messagelist-dev": {},
    "libkf5mimetreeparser-dev": {},
    "libcloudproviders-dev": {},
    "libmalcontent-0-dev": {},
    "librtcom-telepathy-glib-dev": {},
    "libparaglob-dev": {},
    "libkomparediff2-dev": {},
    "libvcflib-dev": {},
    "libskypat-dev": {},
    "libcifti-dev": {},
    "mpb-dev": {},
    "libhipercontracer-dev": {},
    "libinteractive-markers-dev": {},
    "libtoon-dev": {},
    "libpcp-trace2-dev": {},
    "libportsmf-dev": {},
    "libroaring-dev": {},
    "libsmithwaterman-dev": {},
    "libnetpbm10-dev": {},
    "libnetpbm9-dev": {},
    "librandom123-dev": {},
    "libxt-dev": {},
    "libkf5eventviews-dev": {},
    "rofi-dev": {},
    "libshiboken2-dev": {},
    "libmrpt-tclap-dev": {},
    "libtclap-dev": {},
    "simstring-dev": {},
    "tcl-trf-dev": {},
    "libvidstab-dev": {},
    "libframe-dev": {},
    "libxmhtml-dev": {},
    "libanjuta-dev": {},
    "libshape-msgs-dev": {},
    "libmaxflow-dev": {},
    "libopendrim0-dev": {},
    "libfxscintilla-dev": {},
    "libfastjson-dev": {},
    "libomnithread4-dev": {},
    "erlang-dev": {},
    "libopm-common-dev": {},
    "libopm-grid-dev": {},
    "libfcitx5config-dev": {},
    "libgmp-dev": {},
    "libkaccounts-dev": {},
    "libkf5kontactinterface-dev": {},
    "libavahi-core-dev": {},
    "libutfcpp-dev": {},
    "libcpluff0-dev": {},
    "libtss-dev": {},
    "libgegl-dev": {},
    "libatomic-queue-dev": {},
    "libitsol-dev": {},
    "libsword-dev": {},
    "libbamtools-dev": {},
    "libstemmer-dev": {},
    "festival-dev": {},
    "libcos4-dev": {},
    "libcunit1-dev": {},
    "libcunit1-ncurses-dev": {},
    "libstd-msgs-dev": {},
    "nvidia-cg-dev": {},
    "libnifti2-dev": {},
    "libhealpix-cxx-dev": {},
    "libmpcdec-dev": {},
    "libopamgt-dev": {},
    "android-libziparchive-dev": {},
    "libopensm-dev": {},
    "android-liblog-dev": {},
    "wcslib-dev": {},
    "yosys-dev": {},
    "libkf5khtml-dev": {},
    "libbluray-dev": {},
    "libmrpt-opengl-dev": {},
    "libsimavr-dev": {},
    "libsingleapplication-dev": {},
    "liblayershellqtinterface-dev": {},
    "libucimf-dev": {},
    "libt3window-dev": {},
    "libeasyloggingpp-dev": {},
    "libmrpt-gui-dev": {},
    "libmikmod-dev": {},
    "librudecgi-dev": {},
    "libhowardhinnant-date-dev": {},
    "libpluto-lunar-dev": {},
    "libyang-dev": {},
    "liblpsolve55-dev": {},
    "libghmm-dev": {},
    "libkf5ksieve-dev": {},
    "libkf5messagecomposer-dev": {},
    "libkf5messagecore-dev": {},
    "libnabrit-dev": {},
    "libcmor-dev": {},
    "libduo-dev": {},
    "libkmer-dev": {},
    "lua-luv-dev": {},
    "libnetplan-dev": {},
    "libngram-dev": {},
    "libpillowfight-dev": {},
    "libconsensuscore-dev": {},
    "libcpputest-dev": {},
    "libactionlib-dev": {},
    "libkf5kcmutils-dev": {},
    "libtweeny-dev": {},
    "libseqlib-dev": {},
    "libegl-dev": {},
    "libros-rosgraph-msgs-dev": {},
    "libfckit-dev": {},
    "libace-inet-dev": {},
    "libforms-dev": {},
    "freeglut3-dev": {},
    "libqsopt-ex-dev": {},
    "libcrcutil-dev": {},
    "libgnunet-dev": {},
    "libhmsbeagle-dev": {},
    "libmetrohash-dev": {},
    "libion-dev": {},
    "libtidy-dev": {},
    "liblablgtk2-ocaml-dev": {},
    "golang-golang-x-tools-dev": {},
    "libbcg729-dev": {},
    "libffcall-dev": {},
    "libphonenumber-dev": {},
    "libwebm-dev": {},
    "golang-github-mattn-go-pointer-dev": {},
    "libiniparser-dev": {},
    "libkf5auth-dev": {},
    "libmodsecurity-dev": {},
    "libkf5parts-dev": {},
    "libev-libevent-dev": {},
    "libkqueue-dev": {},
    "libprojectm-dev": {},
    "libortp-dev": {},
    "libtelepathy-logger-dev": {},
    "libxy-dev": {},
    "libt3key-dev": {},
    "libvncserver-dev": {},
    "nx-x11proto-core-dev": {},
    "libsv-dev": {},
    "libkarma-dev": {},
    "libutf8.h-dev": {},
    "libfcitx5-qt-dev": {},
    "libfcitx-qt5-dev": {},
    "libfl-dev": {},
    "libgff-dev": {},
    "libglew-dev": {},
    "libglewmx-dev": {},
    "libxcb-glx0-dev": {},
    "libgnustep-gui-dev": {},
    "libgnustep-base-dev": {},
    "libsope-dev": {},
    "libgnustep-dl2-dev": {},
    "librsskit-dev": {},
    "librenaissance0-dev": {},
    "libxtst-dev": {},
    "libxcb-record0-dev": {},
    "libtelepathy-farstream-dev": {},
    "cluster-glue-dev": {},
    "libfox-1.6-dev": {},
    "libsystemc-dev": {},
    "nx-x11proto-render-dev": {},
    "libxcb-render0-dev": {},
    "libddccontrol-dev": {},
    "libmaus2-dev": {},
    "lua-md5-dev": {},
    "libmd-dev": {},
    "librust-sha1collisiondetection-dev": {},
    "libdevil-dev": {},
    "libgiftiio-dev": {},
    "libxcomp-dev": {},
    "liblbfgs-dev": {},
    "libopenjp2-7-dev": {},
    "libdds-dev": {},
    "libmrpt-math-dev": {},
    "libbond-dev": {},
    "libgeometry-msgs-dev": {},
    "libmarble-dev": {},
    "liblapacke-dev": {},
    "libniftiio-dev": {},
    "libznz-dev": {},
    "libxcb-shape0-dev": {},
    "libx11-dev": {},
    "libkpimpkpass-dev": {},
    "libid3-3.8.3-dev": {},
    "libdtkcore-dev": {},
    "liblimesuite-dev": {},
    "libroscpp-msg-dev": {},
    "libpwizlite-dev": {},
    "libmediaart-2.0-dev": {},
    "libvarnishapi-dev": {},
    "libsrtp2-dev": {},
    "libext2fs-dev": {},
    "lua-socket-dev": {},
    "libquantum-dev": {},
    "libosmo-netif-dev": {},
    "libpcp-import1-dev": {},
    "libimath-dev": {},
    "libilmbase-dev": {},
    "libemos-dev": {},
    "libbobcat-dev": {},
    "libivykis-dev": {},
    "libcupsimage2-dev": {},
    "libkpimsmtp-dev": {},
    "libguestfs-gobject-dev": {},
    "libtiff-dev": {},
    "libmate-slab-dev": {},
    "libgooglepinyin0-dev": {},
    "libxcb-sync-dev": {},
    "inventor-dev": {},
    "libkdecorations2-dev": {},
    "libdecoration0-dev": {},
    "libcollection-dev": {},
    "libicecc-dev": {},
    "libkf5mailcommon-dev": {},
    "libtag1-dev": {},
    "libkf5activitiesstats-dev": {},
    "libyazpp-dev": {},
    "libkf5baloowidgets-dev": {},
    "libgrss-dev": {},
    "kuserfeedback-dev": {},
    "libdiagnostic-updater-dev": {},
    "modemmanager-qt-dev": {},
    "libhud2-dev": {},
    "libhud-gtk1-dev": {},
    "libradsec-dev": {},
    "libglobalarrays-dev": {},
    "angelscript-dev": {},
    "golang-github-docker-docker-dev": {},
    "golang-github-opencontainers-runc-dev": {},
    "libkf5kdcraw-dev": {},
    "libkf5i18n-dev": {},
    "mir-renderer-gl-dev": {},
    "libpq-dev": {},
    "libssh-dev": {},
    "libssh-gcrypt-dev": {},
    "libextractor-dev": {},
    "libkf5pimcommon-dev": {},
    "libkf5kipi-dev": {},
    "libqoauth-dev": {},
    "libopencv-core-dev": {},
    "libopencv-features2d-dev": {},
    "libopencv-imgproc-dev": {},
    "libpils2-dev": {},
    "libsprng2-dev": {},
    "libao-dev": {},
    "budgie-core-dev": {},
    "liblv2dynparam1-dev": {},
    "libufpidentity-dev": {},
    "libsignon-qt5-dev": {},
    "libkf5ldap-dev": {},
    "libldap-dev": {},
    "golang-openldap-dev": {},
    "libkf5mbox-dev": {},
    "libkf5mediaplayer-dev": {},
    "libgrooveplayer-dev": {},
    "libgstreamer-plugins-bad1.0-dev": {},
    "librosbag-dev": {},
    "libvlc-dev": {},
    "golang-dlib-dev": {},
    "libemeraldengine-dev": {},
    "libkf5pimtextedit-dev": {},
    "libroslib-dev": {},
    "libblockdev-part-dev": {},
    "libkpimimportwizard-dev": {},
    "libwoff-dev": {},
    "libxcb-dpms0-dev": {},
    "libkf5windowsystem-dev": {},
    "kirigami2-dev": {},
    "iraf-noao-dev": {},
    "libhypre-dev": {},
    "libhypre64-dev": {},
    "libhypre64m-dev": {},
    "liburdf-dev": {},
    "libcamera-calibration-parsers-dev": {},
    "libdieharder-dev": {},
    "libucto-dev": {},
    "libdde-network-utils-dev": {},
    "libxpathselect-dev": {},
    "libkf5akonadicalendar-dev": {},
    "libedit-dev": {},
    "libreadline-dev": {},
    "libkf5akonadimime-dev": {},
    "libkf5mailimporter-dev": {},
    "libwhoopsie-dev": {},
    "libkf5libkdepim-dev": {},
    "py3c-dev": {},
    "golang-github-linuxkit-virtsock-dev": {},
    "libkf5messageviewer-dev": {},
    "libhtscodecs-dev": {},
    "libsocksd0-dev": {},
    "libfontembed-dev": {},
    "libairspy-dev": {},
    "libkf5mailtransport-dev": {},
    "libsynthesis-dev": {},
    "dlt-viewer-dev": {},
    "libimobiledevice-dev": {},
    "libnextcloudsync-dev": {},
    "libowncloudsync-dev": {},
    "libck-dev": {},
    "liblbfgspp-dev": {},
    "libaacs-dev": {},
    "libgoogle-glog-dev": {},
    "libllvmspirvlib-12-dev": {},
    "libllvmspirvlib-dev": {},
    "libdawgdic-dev": {},
    "libimepinyin-dev": {},
    "libmediainfo-dev": {},
    "libgeotranz3-dev": {},
    "librosconsole-bridge-dev": {},
    "libavl-dev": {},
    "liboxli-dev": {},
    "libmurmurhash-dev": {},
    "golang-github-twmb-murmur3-dev": {},
    "libsymmetrica2-dev": {},
    "apache2-dev": {},
    "libotf-trace-dev": {},
    "libopen-trace-format-dev": {},
    "libcmpicppimpl0-dev": {},
    "libzimg-dev": {},
    "libfarmhash-dev": {},
    "libmbt-dev": {},
    "supercollider-dev": {},
    "firebird-dev": {},
    "libcupti-dev": {},
    "libomp-11-dev": {},
    "libomp-12-dev": {},
    "libomp-13-dev": {},
    "libomp-14-dev": {},
    "libcollada2gltfconvert-dev": {},
    "libcgicc-dev": {},
    "libnav-msgs-dev": {},
    "libexpat1-dev": {},
    "libtsl-ordered-map-dev": {},
    "libpipeline-dev": {},
    "libresvg-dev": {},
    "libsdl1.2-compat-dev": {},
    "libsdl1.2-dev": {},
    "libsdl2-dev": {},
    "libsdl-image1.2-dev": {},
    "libsdl2-image-dev": {},
    "libsdl-mixer1.2-dev": {},
    "libsdl2-mixer-dev": {},
    "libsdl-net1.2-dev": {},
    "libsdl2-net-dev": {},
    "libsdl-ttf2.0-dev": {},
    "libsdl2-ttf-dev": {},
    "libvolpack1-dev": {},
    "libgig-dev": {},
    "cimg-dev": {},
    "libflatzebra-dev": {},
    "liboscpack-dev": {},
    "libg810-led-dev": {},
    "libm4rie-dev": {},
    "libmrpt-tfest-dev": {},
    "libxmltok1-dev": {},
    "libp11-kit-dev": {},
    "libxcb-damage0-dev": {},
    "libpyzy-dev": {},
    "libxau-dev": {},
    "libxcb-xf86dri0-dev": {},
    "nx-x11proto-damage-dev": {},
    "libxinerama-dev": {},
    "nx-x11proto-xinerama-dev": {},
    "nx-x11proto-randr-dev": {},
    "libxcb-randr0-dev": {},
    "nx-x11proto-scrnsaver-dev": {},
    "nx-x11proto-xfixes-dev": {},
    "libxpm-dev": {},
    "libbulletml-dev": {},
    "libtinyxml-dev": {},
    "liba52-0.7.4-dev": {},
    "libsamplerate0-dev": {},
    "libxnee-dev": {},
    "libwyhash-dev": {},
    "libfreediameter-dev": {},
    "libgivaro-dev": {},
    "libhts-dev": {},
    "libnotify-dev": {},
    "libcctz-dev": {},
    "persistent-cache-cpp-dev": {},
    "libogg-dev": {},
    "libadmesh-dev": {},
    "libplplot-dev": {},
    "libbam-dev": {},
    "libibmad-dev": {},
    "libmad0-dev": {},
    "libamplsolver-dev": {},
    "libxorg-gtest-dev": {},
    "comerr-dev": {},
    "libnspr4-dev": {},
    "libagg-dev": {},
    "libagg2-dev": {},
    "libmrpt-containers-dev": {},
    "libblockdev-crypto-dev": {},
    "libmrtd-dev": {},
    "libalberta-dev": {},
    "libptexenc-dev": {},
    "libcconv-dev": {},
    "libuninum-dev": {},
    "liballeggl4-dev": {},
    "libatopology-dev": {},
    "libuecc-dev": {},
    "librscode-dev": {},
    "android-libunwind-dev": {},
    "libhtp-dev": {},
    "android-libnativehelper-dev": {},
    "libxmlrpcpp-dev": {},
    "tcl-memchan-dev": {},
    "xfslibs-dev": {},
    "android-libsparse-dev": {},
    "libunwind-dev": {},
    "libunwind-13-dev": {},
    "libunwind-12-dev": {},
    "libunwind-14-dev": {},
    "libangles-dev": {},
    "binutils-dev": {},
    "libantic-dev": {},
    "libbrial-groebner-dev": {},
    "libcrossguid-dev": {},
    "libtsk-dev": {},
    "libheartbeat2-dev": {},
    "libunibreak-dev": {},
    "libappstream-dev": {},
    "libappstream-glib-dev": {},
    "libaprutil1-dev": {},
    "libapr-memcache-dev": {},
    "libzia-dev": {},
    "libczmq-dev": {},
    "libproxy-dev": {},
    "libmrpt-config-dev": {},
    "libarchive-dev": {},
    "libargon2-dev": {},
    "libsundials-dev": {},
    "libgdchart-gd2-noxpm-dev": {},
    "libgdchart-gd2-xpm-dev": {},
    "libcpuinfo-dev": {},
    "libibdm-dev": {},
    "libgeometric-shapes-dev": {},
    "libstarlink-ast-dev": {},
    "libtheora-dev": {},
    "libvorbis-dev": {},
    "libmrpt-topography-dev": {},
    "libjsonparser-dev": {},
    "libopus-dev": {},
    "libmediastreamer-dev": {},
    "libwcstools-dev": {},
    "libhd-dev": {},
    "libqfits-dev": {},
    "python3-sip-dev": {},
    "libxcb-res0-dev": {},
    "libmemtailor-dev": {},
    "libpkgconf-dev": {},
    "libctemplate-dev": {},
    "python-apt-dev": {},
    "libusbauth-configparser-dev": {},
    "libatrildocument-dev": {},
    "libevince-dev": {},
    "libatrilview-dev": {},
    "libzita-resampler-dev": {},
    "libaudclient-dev": {},
    "libdbus-1-dev": {},
    "libmjpegtools-dev": {},
    "libaudiofile-dev": {},
    "libesmtp-dev": {},
    "libb64-dev": {},
    "libhera-dev": {},
    "libpng-dev": {},
    "jskeus-dev": {},
    "libdar-dev": {},
    "libmrpt-maps-dev": {},
    "libminizip-dev": {},
    "libmrpt-io-dev": {},
    "libquazip5-dev": {},
    "libsight-dev": {},
    "libzip-dev": {},
    "libbpfcc-dev": {},
    "libcdb-dev": {},
    "libgd-dev": {},
    "libltdl-dev": {},
    "libdb5.3-dev": {},
    "libuev-dev": {},
    "librdata-dev": {},
    "libzt-dev": {},
    "libglobus-gssapi-gsi-dev": {},
    "libgssglue-dev": {},
    "libsofthsm2-dev": {},
    "libgck-1-dev": {},
    "libopencryptoki-dev": {},
    "libpkcs11-helper1-dev": {},
    "libsquid-dev": {},
    "libflint-arb-dev": {},
    "libinih-dev": {},
    "liboauth-dev": {},
    "libbitmask-dev": {},
    "systemtap-sdt-dev": {},
    "libst-dev": {},
    "librust-onig-sys-dev": {},
    "libb2-dev": {},
    "libmpeg3-dev": {},
    "liblip-dev": {},
    "libptl-dev": {},
    "libblockdev-lvm-dev": {},
    "librust-lua52-sys-dev": {},
    "libblockdev-dev": {},
    "libpyside2-dev": {},
    "libbloom-dev": {},
    "libbluetooth-dev": {},
    "libespeak-ng-dev": {},
    "libxcb-imdkit-dev": {},
    "libbogl-dev": {},
    "libgenometools0-dev": {},
    "guile-gnome2-dev": {},
    "libcrypt-dev": {},
    "libsvn-dev": {},
    "libticables-dev": {},
    "boolstuff-dev": {},
    "libverbiste-dev": {},
    "libopencv-imgcodecs-dev": {},
    "libticonv-dev": {},
    "libquicktime-dev": {},
    "libffi-dev": {},
    "libsqlcipher-dev": {},
    "libsqlite3-dev": {},
    "libtwofish-dev": {},
    "libmm-dev": {},
    "iotjs-dev": {},
    "libminimap2-dev": {},
    "libminimap-dev": {},
    "libbullet-dev": {},
    "libbullet-extras-dev": {},
    "libsnp-sites1-dev": {},
    "libhawknl-dev": {},
    "libwebsockets-dev": {},
    "libnuma-dev": {},
    "libcacard-dev": {},
    "libblis-openmp-dev": {},
    "libblis-pthread-dev": {},
    "libblis-serial-dev": {},
    "libopenblas-openmp-dev": {},
    "libopenblas-pthread-dev": {},
    "libopenblas-serial-dev": {},
    "libopenblas64-openmp-dev": {},
    "libopenblas64-pthread-dev": {},
    "libopenblas64-serial-dev": {},
    "libpthreadpool-dev": {},
    "libhiredis-dev": {},
    "qtbase5-dev": {},
    "qtbase5-gles-dev": {},
    "qt6-base-dev": {},
    "libopenni2-dev": {},
    "libcanna1g-dev": {},
    "libpsm2-dev": {},
    "libsaclib-dev": {},
    "libcfitsio-dev": {},
    "libmstoolkit-dev": {},
    "libopencl-clang-12-dev": {},
    "libopencl-clang-dev": {},
    "libccp4-dev": {},
    "libcdd-dev": {},
    "libudf-dev": {},
    "libhe5-hdfeos-dev": {},
    "libhdfeos-dev": {},
    "libcgns-dev": {},
    "libsexp-dev": {},
    "libcif-dev": {},
    "libcinnamon-control-center-dev": {},
    "libunity-control-center-dev": {},
    "libcinnamon-desktop-dev": {},
    "libgnome-desktop-3-dev": {},
    "libgnome-bg-4-dev": {},
    "libgnome-desktop-4-dev": {},
    "libgnome-rr-4-dev": {},
    "libcinnamon-menu-3-dev": {},
    "libgnome-menu-3-dev": {},
    "libcjson-dev": {},
    "libclass-loader-dev": {},
    "libpeony-dev": {},
    "pidgin-dev": {},
    "librust-atk-sys-dev": {},
    "librust-gdk-pixbuf-sys-dev": {},
    "librust-gdk-sys-dev": {},
    "librust-gdk4-sys-dev": {},
    "librust-gdk4-x11-sys-dev": {},
    "librust-gio-sys-dev": {},
    "librust-glib-sys-dev": {},
    "librust-gobject-sys-dev": {},
    "librust-graphene-sys-dev": {},
    "librust-gsk4-sys-dev": {},
    "librust-gstreamer-audio-sys-dev": {},
    "librust-gstreamer-base-sys-dev": {},
    "librust-gstreamer-sys-dev": {},
    "librust-gstreamer-video-sys-dev": {},
    "librust-gtk-sys-dev": {},
    "librust-gtk4-sys-dev": {},
    "librust-libhandy-sys-dev": {},
    "librust-pango-sys-dev": {},
    "golang-github-erikdubbelboer-gspt-dev": {},
    "libclutter-1.0-dev": {},
    "libcmrt-dev": {},
    "libigfxcmrt-dev": {},
    "libcminpack-dev": {},
    "minpack-dev": {},
    "libcmocka-dev": {},
    "libbrahe-dev": {},
    "libmapserver-dev": {},
    "uthash-dev": {},
    "libsquirrel-dev": {},
    "libcogl-pango-dev": {},
    "libcogl-dev": {},
    "libcollada-dom-dev": {},
    "libcolord-gtk-dev": {},
    "libcolord-dev": {},
    "libconcurrentqueue-dev": {},
    "libcmap-dev": {},
    "libsam-dev": {},
    "libcpdb-libs-common-dev": {},
    "libgdal-dev": {},
    "librasterlite2-dev": {},
    "libsqlite0-dev": {},
    "librw-dev": {},
    "golang-github-hashicorp-consul-dev": {},
    "libcryptominisat5-dev": {},
    "libpstreams-dev": {},
    "libcsv-dev": {},
    "libfccp-dev": {},
    "ctapi-dev": {},
    "libctapimkt1-dev": {},
    "libtowitoko-dev": {},
    "cthreadpool-dev": {},
    "libctl-dev": {},
    "libppd-dev": {},
    "libffmpegthumbnailer-dev": {},
    "libofa0-dev": {},
    "libtfm-dev": {},
    "libxcb-present-dev": {},
    "libdart-external-imgui-dev": {},
    "libimgui-dev": {},
    "libdart-external-lodepng-dev": {},
    "libdapl-dev": {},
    "liburiparser-dev": {},
    "libtimezonemap1-dev": {},
    "libgdbm-compat-dev": {},
    "liblockfile-dev": {},
    "libdjconsole-dev": {},
    "libhdf5-mpich-dev": {},
    "libhdf5-openmpi-dev": {},
    "libhdf5-dev": {},
    "libmumps-headers-dev": {},
    "libmpich-dev": {},
    "libmrpt-kinematics-dev": {},
    "libdaemon-dev": {},
    "libax25-dev": {},
    "libmariadb-dev": {},
    "libmysqlclient-dev": {},
    "libmicroprofile-dev": {},
    "389-ds-base-dev": {},
    "slapi-dev": {},
    "libdkim-dev": {},
    "libopendkim-dev": {},
    "libpfs-dev": {},
    "libmpc-dev": {},
    "libdlt-dev": {},
    "liblua5.1-0-dev": {},
    "liblua5.2-dev": {},
    "liblua5.3-dev": {},
    "liblua5.4-dev": {},
    "libluajit-5.1-dev": {},
    "libtexlua53-dev": {},
    "libtexluajit-dev": {},
    "libzookeeper-mt-dev": {},
    "libzookeeper-st-dev": {},
    "libogdi-dev": {},
    "libdpdk-dev": {},
    "libdogleg-dev": {},
    "libpetsc-complex3.15-dev": {},
    "libpetsc-real3.15-dev": {},
    "libpetsc64-complex3.15-dev": {},
    "libpetsc64-real3.15-dev": {},
    "libscotch-dev": {},
    "libjson-glib-dev": {},
    "libfec-dev": {},
    "libdumb1-dev": {},
    "librm-dev": {},
    "libunity-dev": {},
    "libdw-dev": {},
    "libdwarf-dev": {},
    "libedlib-dev": {},
    "chezscheme-dev": {},
    "libteem-dev": {},
    "libespeak-ng-libespeak-dev": {},
    "libespeak-dev": {},
    "libedataserver1.2-dev": {},
    "libgnomecanvas2-dev": {},
    "libexempi-dev": {},
    "libxmp-dev": {},
    "libexodusii-dev": {},
    "libtdb-dev": {},
    "libf2c2-dev": {},
    "libvmmlib-dev": {},
    "libfcgi-dev": {},
    "librtmidi-dev": {},
    "libxcb-xkb-dev": {},
    "libraw1394-dev": {},
    "fftw-dev": {},
    "libmkl-dev": {},
    "libfftw3-mpi-dev": {},
    "libfftw3-dev": {},
    "libplot-dev": {},
    "libfinal-dev": {},
    "liblz4-dev": {},
    "libladspa-ocaml-dev": {},
    "libflxmlrpc-dev": {},
    "libsphere-dev": {},
    "libfp16-dev": {},
    "libpsimd-dev": {},
    "librust-ipconfig-dev": {},
    "librust-libnotcurses-sys-dev": {},
    "libatlas-base-dev": {},
    "fst-dev": {},
    "libftdi-dev": {},
    "libftdi1-dev": {},
    "libftp-dev": {},
    "libxpa-dev": {},
    "libfxt-dev": {},
    "liblitl-dev": {},
    "libga-dev": {},
    "libgail-dev": {},
    "libgail-3-dev": {},
    "libplist-dev": {},
    "libignition-gui-dev": {},
    "libignition-msgs5-dev": {},
    "libignition-msgs-dev": {},
    "libgbm-dev": {},
    "vulkan-validationlayers-dev": {},
    "libxxhash-dev": {},
    "libgctp-dev": {},
    "libproj-dev": {},
    "libgdcm-dev": {},
    "libjalali-dev": {},
    "libjpeg-turbo8-dev": {},
    "libjpeg9-dev": {},
    "libjpeg62-dev": {},
    "gemmi-dev": {},
    "libgeners-dev": {},
    "libgeonames-dev": {},
    "libgeotiff-dev": {},
    "libgtkgl2.0-dev": {},
    "libgetfem++-dev": {},
    "libgmm++-dev": {},
    "libgf2x-dev": {},
    "libpari-dev": {},
    "liblightdm-qt5-3-dev": {},
    "qtbase5-private-dev": {},
    "qtbase5-private-gles-dev": {},
    "qt6-base-private-dev": {},
    "ss-dev": {},
    "libgl2ps-dev": {},
    "libformsgl-dev": {},
    "libnauty2-dev": {},
    "golang-gir-gobject-2.0-dev": {},
    "libsoqt520-dev": {},
    "golang-github-mendersoftware-openssl-dev": {},
    "libglpk-dev": {},
    "libspirv-cross-c-shared-dev": {},
    "libganglia1-dev": {},
    "libgmlib-dev": {},
    "libzipios++-dev": {},
    "libgmock-dev": {},
    "picojson-dev": {},
    "golang-github-mattn-go-sqlite3-dev": {},
    "libsegyio-dev": {},
    "libmms-dev": {},
    "libgnome-bluetooth-ui-3.0-dev": {},
    "libgnome-bluetooth-dev": {},
    "gnome-settings-daemon-dev": {},
    "unity-settings-daemon-dev": {},
    "libhamlib-dev": {},
    "qttools5-private-dev": {},
    "qt6-tools-private-dev": {},
    "libgps-dev": {},
    "libimage-geometry-dev": {},
    "libgsasl-dev": {},
    "libgst-dev": {},
    "libgtest-dev": {},
    "libgtextutils-dev": {},
    "golang-github-libvirt-libvirt-go-dev": {},
    "libgtk2.0-dev": {},
    "libgtk-3-dev": {},
    "libgtk-4-dev": {},
    "libopenrawgnome-dev": {},
    "libgtkdatabox-dev": {},
    "libgtksourceview-3.0-dev": {},
    "libgtksourceview-4-dev": {},
    "libgtksourceview-5-dev": {},
    "libgtkspell-dev": {},
    "libgtkspell3-3-dev": {},
    "libscm-dev": {},
    "libgupnp-av-1.0-dev": {},
    "libgupnp-dlna-2.0-dev": {},
    "libmxml-dev": {},
    "libpaper-dev": {},
    "libosptk-dev": {},
    "libmrcal-dev": {},
    "libgzstream-dev": {},
    "libtl-parser-dev": {},
    "libhavege-dev": {},
    "libhaapi-dev": {},
    "zfcp-hbaapi-dev": {},
    "libhbaapi-dev": {},
    "libnetcdf-dev": {},
    "libnetcdf-mpi-dev": {},
    "libnetcdf-pnetcdf-dev": {},
    "libhidapi-dev": {},
    "libhkl-dev": {},
    "libhpdf-dev": {},
    "libidn-dev": {},
    "libhttp-parser-dev": {},
    "libnvidia-ml-dev": {},
    "golang-github-google-cadvisor-dev": {},
    "libident-dev": {},
    "libignition-transport-dev": {},
    "libignition-transport8-dev": {},
    "libossp-sa-dev": {},
    "libraft-dev": {},
    "librecode-dev": {},
    "tcl-itcl4-dev": {},
    "itcl3-dev": {},
    "tk-itk4-dev": {},
    "itk3-dev": {},
    "libbinio-dev": {},
    "libjerasure-dev": {},
    "libjemalloc-dev": {},
    "libjsmn-dev": {},
    "libviennacl-dev": {},
    "libjwt-dev": {},
    "libjwt-gnutls-dev": {},
    "libpcre3-dev": {},
    "libnacl-dev": {},
    "libkeybinder-3.0-dev": {},
    "libkeybinder-dev": {},
    "libkissfft-dev": {},
    "liblcm-dev": {},
    "libmrpt-graphs-dev": {},
    "libmodplug-dev": {},
    "libopenmpt-modplug-dev": {},
    "libappindicator-dev": {},
    "libappindicator3-dev": {},
    "libayatana-appindicator-dev": {},
    "libayatana-appindicator3-dev": {},
    "libayatana-ido3-dev": {},
    "libido3-0.1-dev": {},
    "libayatana-indicator-dev": {},
    "libayatana-indicator3-dev": {},
    "libindicator-dev": {},
    "libindicator3-dev": {},
    "libbson-dev": {},
    "libmongo-client-dev": {},
    "libconfig-dev": {},
    "libdframeworkdbus-dev": {},
    "libdbusextended-qt5-dev": {},
    "libdtkgui-dev": {},
    "libdtkwidget-dev": {},
    "liboauth2-apache-dev": {},
    "libexif-dev": {},
    "libiptcdata0-dev": {},
    "libfm-dev": {},
    "libfm-extra-dev": {},
    "libfungw-dev": {},
    "libglade2-dev": {},
    "libgladeui-dev": {},
    "libgweather-3-dev": {},
    "libgweather-4-dev": {},
    "libhandy-0.0-dev": {},
    "libhandy-1-dev": {},
    "libinput-dev": {},
    "libsane-dev": {},
    "liblzf-dev": {},
    "libmaloc-dev": {},
    "libxsettings-client-dev": {},
    "libxsettings-dev": {},
    "libsndfile1-dev": {},
    "libvulkan-dev": {},
    "libntlm0-dev": {},
    "libsecret-1-dev": {},
    "libsoup2.4-dev": {},
    "libsoup-3.0-dev": {},
    "liblablgtk3-ocaml-dev": {},
    "libqt5-ukui-style-dev": {},
    "libtpms-dev": {},
    "libusb-1.0-0-dev": {},
    "libmodbus-dev": {},
    "libosmo-abis-dev": {},
    "libunique-dev": {},
    "liblmdb-dev": {},
    "golang-github-bmatsuo-lmdb-go-dev": {},
    "libmtbl-dev": {},
    "lua-filesystem-dev": {},
    "libmuparser-dev": {},
    "libspnav-dev": {},
    "libmate-sensors-applet-plugin-dev": {},
    "libsensors-applet-plugin-dev": {},
    "libscotchmetis-dev": {},
    "libmetis-dev": {},
    "libmfx-dev": {},
    "libvpl-dev": {},
    "libmircookie-dev": {},
    "librep-dev": {},
    "libmpeg2-4-dev": {},
    "libyaml-dev": {},
    "libmrpt-poses-dev": {},
    "libstb-dev": {},
    "libmrpt-obs-dev": {},
    "libmrpt-typemeta-dev": {},
    "libre-dev": {},
    "libmassivethreads-dev": {},
    "libvdpau-dev": {},
    "libxcb-xvmc0-dev": {},
    "libxc-dev": {},
    "libneon27-dev": {},
    "libneon27-gnutls-dev": {},
    "libghc-hoogle-dev": {},
    "libsubunit-dev": {},
    "libsysfs-dev": {},
    "libopenlibm-dev": {},
    "liboce-foundation-dev": {},
    "libocct-foundation-dev": {},
    "liboce-modeling-dev": {},
    "libocct-data-exchange-dev": {},
    "libvorbisidec-dev": {},
    "libonig-dev": {},
    "libotf-dev": {},
    "librust-findshlibs-dev": {},
    "librust-freetype-dev": {},
    "libopencv-photo-dev": {},
    "libopencv-video-dev": {},
    "libopencv-videoio-dev": {},
    "libself-test-dev": {},
    "libopusfile-dev": {},
    "libtalloc-dev": {},
    "librsl-dev": {},
    "libtinyobjloader-dev": {},
    "librostlab3-dev": {},
    "libvtk7-qt-dev": {},
    "libvtk9-qt-dev": {},
    "libscotchparmetis-dev": {},
    "libparmetis-dev": {},
    "libpcl-msgs-dev": {},
    "libpixman-1-dev": {},
    "libpoppler-cpp-dev": {},
    "libpoppler-glib-dev": {},
    "libpoppler-qt5-dev": {},
    "libpsm-infinipath1-dev": {},
    "librust-psm-dev": {},
    "libqdbm-dev": {},
    "libvistaio-dev": {},
    "qtkeychain-qt5-dev": {},
    "qtkeychain-qt6-dev": {},
    "librhash-dev": {},
    "libstd-srvs-dev": {},
    "librtaudio-dev": {},
    "libeantic-dev": {},
    "libsdformat-dev": {},
    "libsdformat9-dev": {},
    "libsuperlu-dist-dev": {},
    "libshp-dev": {},
    "libshout-dev": {},
    "libshout-idjc-dev": {},
    "libsidplayfp-dev": {},
    "libresid-builder-dev": {},
    "libsidutils-dev": {},
    "libsmi2-dev": {},
    "libspice-client-glib-2.0-dev": {},
    "libspice-server-dev": {},
    "librust-stacker-dev": {},
    "libstarpu-dev": {},
    "libstarpu-contrib-dev": {},
    "libstonith1-dev": {},
    "tcl-expect-dev": {},
    "libsuperlu-dev": {},
    "libt3highlight-dev": {},
    "librust-tree-sitter-highlight-dev": {},
    "libwgdb-dev": {},
    "libtommath-dev": {},
    "libtf2-msgs-dev": {},
    "libvpx-dev": {},
    "libopenh264-dev": {},
    "libusrsctp-dev": {},
    "libutf8proc-dev": {},
    "libxqilla-dev": {},
    "libvulkan-volk-dev": {},
    "libvte-2.91-dev": {},
    "libvterm-dev": {},
    "libjavascriptcoregtk-4.0-dev": {},
    "libjavascriptcoregtk-4.1-dev": {},
    "libwpewebkit-1.0-dev": {},
    "libwebkit2gtk-4.0-dev": {},
    "libwebkit2gtk-4.1-dev": {},
    "libblis64-openmp-dev": {},
    "libblis64-pthread-dev": {},
    "libblis64-serial-dev": {},
    "qt3d5-dev": {},
    "qt6-3d-dev": {},
    "qtmultimedia5-dev": {},
    "qt6-multimedia-dev": {},
    "qtconnectivity5-dev": {},
    "qt6-connectivity-dev": {},
    "libqt5charts5-dev": {},
    "libqt6charts6-dev": {},
    "qt6-scxml-dev": {},
    "libqt6core5compat6-dev": {},
    "libqt5datavisualization5-dev": {},
    "libqt6datavisualization6-dev": {},
    "libqt6opengl6-dev": {},
    "libqt5networkauth5-dev": {},
    "libqt6networkauth6-dev": {},
    "libqt5opengl5-dev": {},
    "qtdeclarative5-private-dev": {},
    "qt6-declarative-private-dev": {},
    "qtdeclarative5-dev": {},
    "qt6-declarative-dev": {},
    "qtpdf5-dev": {},
    "qt6-pdf-dev": {},
    "qtpositioning5-dev": {},
    "qt6-positioning-dev": {},
    "qtquickcontrols2-5-private-dev": {},
    "qtquickcontrols2-5-dev": {},
    "libqt5remoteobjects5-dev": {},
    "qt6-remoteobjects-dev": {},
    "libqt5scxml5-dev": {},
    "libqt5sensors5-dev": {},
    "libqt6sensors6-dev": {},
    "libqt5serialbus5-dev": {},
    "libqt6serialbus6-dev": {},
    "libqt5serialport5-dev": {},
    "libqt6serialport6-dev": {},
    "libqt5svg5-dev": {},
    "libqt6svg6-dev": {},
    "libqt5virtualkeyboard5-dev": {},
    "libqt6virtualkeyboard6-dev": {},
    "libqt5waylandclient5-dev": {},
    "qt6-wayland-dev": {},
    "libqt5waylandcompositor5-dev": {},
    "libqt5webchannel5-dev": {},
    "libqt6webchannel6-dev": {},
    "qtwebengine5-private-dev": {},
    "qt6-webengine-private-dev": {},
    "qtwebengine5-dev": {},
    "qt6-webengine-dev": {},
    "libqt5websockets5-dev": {},
    "libqt6websockets6-dev": {},
    "libqt5webview5-dev": {},
    "qt6-webview-dev": {},
    "libvisp-dev": {},
    "libvisp-core-dev": {},
    "libvisp-sensor-dev": {},
    "libvisp-ar-dev": {},
    "libvisp-vs-dev": {},
    "libvisp-robot-dev": {},
    "libvisp-visual-features-dev": {},
    "libvisp-vision-dev": {},
    "libvisp-imgproc-dev": {},
    "libvisp-gui-dev": {},
    "libvisp-detection-dev": {},
    "libvisp-io-dev": {},
    "libvisp-blob-dev": {},
    "libvisp-klt-dev": {},
    "libvisp-mbt-dev": {},
    "libvisp-me-dev": {},
    "libvisp-tt-dev": {},
    "libvisp-tt-mi-dev": {},
    "libxcb-dri2-0-dev": {},
    "libxcb-dri3-dev": {},
    "libzeitgeist-dev": {},
    "libzeitgeist-2.0-dev": {},
    "libgfortran-10-dev": {},
    "libgfortran-11-dev": {},
    "libgfortran-12-dev": {},
    "libgfortran-9-dev": {},
    "libgccjit-10-dev": {},
    "libgccjit-11-dev": {},
    "libgccjit-12-dev": {},
    "libgccjit-9-dev": {},
    "libctypes-ocaml-dev": {},
    "libintegers-ocaml-dev": {},
    "libslepc-complex3.15-dev": {},
    "libslepc-real3.15-dev": {},
    "libslepc64-complex3.15-dev": {},
    "libslepc64-real3.15-dev": {},
    "libpmix-dev": {},
    "libcomedi-dev": {},
    "libvixl-dev": {},
    "liblgpio-dev": {},
    "librgpio-dev": {},
    "liblzo2-dev": {},
    "libucl-dev": {},
    "libsmbclient-dev": {},
    "golang-github-ostreedev-ostree-go-dev": {},
    "golang-github-sjoerdsimons-ostree-go-dev": {}
}